{
  "$schema": "https://developer.microsoft.com/json-schemas/spfx/client-side-web-part-manifest.schema.json",
  "id": "4ab6d82d-c7bf-437b-bf19-53cf1b41a4ef",
  "alias": "NewsWebPart",
  "componentType": "WebPart",

 
  "version": "*",
  "manifestVersion": 2,


  "requiresCustomScript": false,
  "supportedHosts": ["SharePointWebPart", "TeamsPersonalApp", "TeamsTab", "SharePointFullPage"],
  "supportsThemeVariants": true,

  "preconfiguredEntries": [{
    "groupId": "5c03119e-3074-46fd-976b-c60198311f70", 
    "group": { "default": "Advanced" },
    "title": { "default": "news" },
    "description": { "default": "news description" },
    "officeFabricIconFontName": "Page",
    "properties": {
      "description": "news"
    }
  }]
}
